aws_mfa_spok-0.0.14.data/scripts/aws-mfa
aws_mfa_spok-0.0.14.data/scripts/aws-mfa-spok
aws_mfa_spok-0.0.14.dist-info/METADATA
aws_mfa_spok-0.0.14.dist-info/RECORD
aws_mfa_spok-0.0.14.dist-info/WHEEL
aws_mfa_spok-0.0.14.dist-info/entry_points.txt
aws_mfa_spok-0.0.14.dist-info/top_level.txt
awsmfa/__init__.py
awsmfa/config.py
awsmfa/util.py
