Metadata-Version: 2.1
Name: aws-mfa-spok
Version: 0.0.14
Summary: Manage AWS MFA Security Credentials
Home-page: https://github.com/jasondbakerspok/aws-mfa
Author: Jason Baker
Author-email: jason.baker@spok.com
License: MIT
Platform: UNKNOWN
Requires-Dist: boto3
